petrodc/__init__.py
petrodc/plot.py
petrodc/ags/__init__.py
petrodc/ags/sr_006.py
petrodc/npd/__init__.py
petrodc/npd/wellbore.py
petrodc/usgs_eros/__init__.py
petrodc/usgs_eros/elevation.py
petrodc-0.1.10.dist-info/LICENSE
petrodc-0.1.10.dist-info/METADATA
petrodc-0.1.10.dist-info/WHEEL
petrodc-0.1.10.dist-info/top_level.txt
petrodc-0.1.10.dist-info/RECORD
