Metadata-Version: 2.1
Name: petrodc
Version: 0.1.10
Summary: Petroleum Data Collector
Home-page: UNKNOWN
Author: Juan Camilo Gonzalez Angarita
Author-email: juan@prowellplan.com
License: LGPL v3
Keywords: petroleum data collector operations wellbore oil gas
Platform: UNKNOWN
Classifier: Programming Language :: Python :: 3
Classifier: License :: OSI Approved :: GNU Lesser General Public License v3 (LGPLv3)
Classifier: Natural Language :: English
Classifier: Topic :: Scientific/Engineering
Classifier: Topic :: Software Development
Classifier: Topic :: Software Development :: Libraries
Classifier: Topic :: Utilities
Requires-Dist: pandas
Requires-Dist: requests
Requires-Dist: numpy
Requires-Dist: plotly
Requires-Dist: lasio
